LICENSE
MANIFEST.in
README.rst
setup.cfg
setup.py
admin_commands/__init__.py
admin_commands/admin.py
admin_commands/app_settings.py
admin_commands/apps.py
admin_commands/forms.py
admin_commands/models.py
admin_commands/tests.py
admin_commands/utils.py
admin_commands/views.py
admin_commands/migrations/0001_initial.py
admin_commands/migrations/__init__.py
admin_commands/templates/admin_commands/execute_command.html
django_admin_commands2.egg-info/PKG-INFO
django_admin_commands2.egg-info/SOURCES.txt
django_admin_commands2.egg-info/dependency_links.txt
django_admin_commands2.egg-info/requires.txt
django_admin_commands2.egg-info/top_level.txt